{
  "cn": [
    {
      "title": "概览",
      "children": [
        {
          "title": "EMQ X Neuron 简介",
          "path": "./"
        }
      ]
    },
    {
      "title": "安装",
      "path": "getting-started/install"
    },
    {
      "title": "快速教程",
      "path": "getting-started/quick_start"
    },
    {
      "title": "网页使用介绍",
      "children": [
        {
          "title": "登录",
          "path": "dashboard-interface/login"
        },
        {
          "title": "首页",
          "path": "dashboard-interface/home"
        },
        {
          "title": "监控",
          "path": "dashboard-interface/monitoring"
        },
        {
          "title": "配置",
          "path": "dashboard-interface/configuration"
        },
        {
          "title": "管理",
          "path": "dashboard-interface/management"
        }
      ]
    },
    {
      "title": "Neuron 驱动地址格式",
      "path": "address-format/neuron2.x-driver"
    },
    {
      "title": "API 文档",
      "path": "api-function/neuron2.x-api"
    },
    {
      "title": "Error Codes",
      "path": "error-code/neuron2.x-error-code"
    },
    {
      "title": "MQTT订阅主题",
      "path": "mqtt-topic/neuron2.x-mqtt-topics"
    }
  ],
  "en": [
    {
      "title": "Introduction",
      "children": [
        {
          "title": "EMQ X Neuron",
          "path": "./"
        }
      ]
    },
    {
      "title": "Neuron Driver Address Format",
      "path": "address-format/neuron2.x-driver"
    },
    {
      "title": "API",
      "path": "api-function/neuron2.x-api"
    },
    {
      "title": "Error Codes",
      "path": "error-code/neuron2.x-error-code"
    },
    {
      "title": "MQTT Topics",
      "path": "mqtt-topic/neuron2.x-mqtt-topics"
    }
  ]
}